{"title":"小L的跳棋[国家集训队2013]","time_limit":1000,"memory_limit":128,"tags":[],"operation":{"submit":"https://syzoj.com/problem/270#submit_code","submissions":"https://syzoj.com/submissions?problem_id=270","statistics":"https://syzoj.com/problem/270/statistics/fastest","testdata":"https://syzoj.com/problem/270/testdata","discussion":"https://syzoj.com/discussion/problem/270"},"statement":[{"title":"题目描述","type":"description","format":"markdown","require":["katex"],"content":"　　小L发明了一种新的跳棋游戏，规则为在一个一维棋盘上，一共n个点，每个点都有自己的权值，最初点标号为1，其他点标号按顺序递增，每次玩家可以进行两种操作 :  \r\n　　0 : 从1出发，每次向后跳(l - 1)个点，所有经过的格子上的值都增加k，当跳出n个点的范围时该操作停止  \r\n　　1 : 给定l和r，统计l ~ r内 ( 包含l和r ) 的所有点的权值和，如果区间和与系统的当前随机值相同，则可以赢得奖品  \r\n　　小T决定尝试一下这个游戏，但是他并不想获胜，他只是想给小L找麻烦，于是向小L的游戏服务器发送了大量的操作，小L请你帮他快速算出小T发送的所有操作的结果\r\n　　( 我编不下去了.. 这道题就这样吧.... BY XTT"},{"title":"输入格式","type":"input_format","format":"markdown","require":["katex"],"content":"第一行两个整数，为n和m，分别表示棋子总数和操作个数  \r\n接下来一行n个整数，表示每一个棋子对应的值  \r\n接下来m行每行3个整数，分别表示操作类型和操作对应所需的参数"},{"title":"输出格式","type":"output_format","format":"markdown","require":["katex"],"content":"对于每一个1操作，输出统计结果"},{"title":"样例","type":"example","format":"markdown","require":["katex"],"content":"####输入样例\r\n```\r\n4 5\r\n3 7 4 2\r\n1 1 4\r\n0 2 9\r\n1 3 3\r\n0 1 1\r\n1 1 4\r\n```\r\n####输出样例\r\n```\r\n16\r\n13\r\n38\r\n```\r\n####样例解释\r\n第一个操作询问1 ~ 4的权值和，为3 + 7 + 4 + 2 = 16  \r\n第二个操作更改了1, 3(1 + 2)的值，原序列变为12 7 13 2  \r\n第三个操作询问3 ~ 3的权值和，为13 + 13 = 26  \r\n第四个操作更改了1, 2(1 + 1), 3(2 + 1), 4(3 + 1)的值，原序列变为13 8 14 3  \r\n第一个操作询问1 ~ 4的权值和，为13 + 8 + 14 + 3 = 38"},{"title":"数据范围与提示","type":"limit_and_hint","format":"markdown","require":["katex"],"content":"对于20%的测试数据 n, m <= 10  \r\n对于50%的测试数据 n, m <= 3000  \r\n对于100%的测试数据 1 <= n, m <= 100000, 1<= k, 原序列中的值 <= 100000"}]}