{"title":"「一本通 2.2 例 1」剪花布条","time_limit":1000,"memory_limit":512,"tags":[],"operation":{"submit":"https://syzoj.com/problem/398#submit_code","submissions":"https://syzoj.com/submissions?problem_id=398","statistics":"https://syzoj.com/problem/398/statistics/fastest","testdata":"https://syzoj.com/problem/398/testdata","discussion":"https://syzoj.com/discussion/problem/398"},"statement":[{"title":"题目描述","type":"description","format":"markdown","require":["katex"],"content":"**原题来自：[HDU 2087](http://acm.hdu.edu.cn/showproblem.php?pid=2087)**\r\n\r\n一块花布条，里面有些图案，另有一块直接可用的小饰条，里面也有一些图案。对于给定的花布条和小饰条，计算一下能从花布条中尽可能剪出几块小饰条来呢？"},{"title":"输入格式","type":"input_format","format":"markdown","require":["katex"],"content":"输入数据为多组数据，读取到 `#` 字符时结束。每组数据仅有一行，为由空格分开的花布条和小饰条。花布条和小饰条都是用可见 ASCII 字符表示的，不会超过 $1000$ 个字符。\r\n\r\n**注意：这个 `#` 应为单个字符。若某字符串开头有 `#`，不意味着读入结束！**"},{"title":"输出格式","type":"output_format","format":"markdown","require":["katex"],"content":"对于每组数据，输出一行一个整数，表示能从花纹布中剪出的最多小饰条个数。"},{"title":"样例","type":"example","format":"markdown","require":["katex"],"content":"#### 样例输入\r\n\r\n```plain\r\nabcde a3\r\naaaaaa aa\r\n#\r\n```\r\n\r\n#### 样例输出\r\n\r\n```plain\r\n0\r\n3\r\n```"},{"title":"数据范围与提示","type":"limit_and_hint","format":"markdown","require":["katex"],"content":"对于全部数据，字符串长度 $\\leq 1000$。"}]}