{"title":"1-06A. nocriz送温暖","time_limit":1125,"memory_limit":512,"tags":["2019小学期","数据结构","前缀和","逆元"],"operation":{"submit":"https://oj.xjtuicpc.com/problem/1048#submit_code","submissions":"https://oj.xjtuicpc.com/submissions?problem_id=1048","statistics":"https://oj.xjtuicpc.com/problem/1048/statistics/fastest","testdata":"https://oj.xjtuicpc.com/problem/1048/testdata","discussion":"https://oj.xjtuicpc.com/discussion/problem/1048"},"statement":[{"title":"题目描述","type":"description","format":"markdown","require":["katex"],"content":"`nocriz`是个友善的出题人。\r\n\r\n有 $n$ 个数 $a_1, a_2, \\ldots, a_n$ ，有 $q$ 次询问，每次问 $a_l \\times a_{l+1} \\times \\ldots \\times a_{r} \\mod 998,244,353$ 的值。"},{"title":"输入格式","type":"input_format","format":"markdown","require":["katex"],"content":"第一行一行两个整数 $n,\\ q$ 。\r\n\r\n第二行一行 $n$ 个整数 $a_1, a_2, \\ldots, a_n$ 。\r\n\r\n接下来 $q$ 行，每行两个整数 $l_i,\\ r_i$ 。"},{"title":"输出格式","type":"output_format","format":"markdown","require":["katex"],"content":"输出 $q$ 行，每行一个整数，代表答案。"},{"title":"样例","type":"example","format":"markdown","require":["katex"],"content":"#### 样例输入\r\n```plain\r\n10 2\r\n2 1 7 3 7 1 4 2 9 7\r\n1 2\r\n1 10\r\n```\r\n\r\n#### 样例输出\r\n```plain\r\n2\r\n148176\r\n```"},{"title":"数据范围与提示","type":"limit_and_hint","format":"markdown","require":["katex"],"content":"$1 \\le n,\\ q \\le 2 \\cdot 10^5$\r\n\r\n$1 \\le a_i \\le 998,244,352$\r\n\r\n**Hint**\r\n\r\n本题被弱化了。\r\n\r\n由于输入量较大，请避免使用cin/cout，使用较为快速的scanf/printf。"}]}