{"title":"1-09F. jwp的游戏策划","time_limit":750,"memory_limit":512,"tags":["2019小学期"],"operation":{"submit":"https://oj.xjtuicpc.com/problem/1074#submit_code","submissions":"https://oj.xjtuicpc.com/submissions?problem_id=1074","statistics":"https://oj.xjtuicpc.com/problem/1074/statistics/fastest","testdata":"https://oj.xjtuicpc.com/problem/1074/testdata","discussion":"https://oj.xjtuicpc.com/discussion/problem/1074"},"statement":[{"title":"题目描述","type":"description","format":"markdown","require":["katex"],"content":"jwp创造了一款新的游戏，这是一个世界观宏大的战争游戏，有n个角色职业，每个职业要占用 $cost_i$ 点的资源值，jwp需要设定游戏的总资源值all，使得至少有一组所有玩家选择职业的组合可以不加浪费的利用所有的资源值，即如果选择每个职业的玩家数量为 $num_i$ ，那么关于 $num_i$ 的方程 $\\sum_{i = 1}^{n}{cost_i * num_i} = all$ 至少有一组非负整数解，这里我们不虚要考虑玩家的总数量，即玩家总数量可以是任意非负整数。由于技术手段的限制， $all$ 有一个范围 $[all_l,\\ all_r]$ ，现在jwp希望知道，在这个范围内有多少个可能的 $all$ 值，使得他可以达成上述资源的不加浪费的分配。"},{"title":"输入格式","type":"input_format","format":"markdown","require":["katex"],"content":"第一行三个整数 $n,\\ all_l,\\ all_r$ 。\r\n\r\n第二行 $n$ 个整数 $cost_i$ 。"},{"title":"输出格式","type":"output_format","format":"markdown","require":["katex"],"content":"输出一行一个整数，表示可能 $all$ 值的数量。"},{"title":"样例","type":"example","format":"markdown","require":["katex"],"content":"#### 样例输入\r\n```plain\r\n3 1 10\r\n3 4 5\r\n```\r\n\r\n#### 样例输出\r\n```plain\r\n8\r\n```"},{"title":"数据范围与提示","type":"limit_and_hint","format":"markdown","require":["katex"],"content":"$1 \\le n \\le 10$\r\n\r\n$1 \\le cost_i \\le 10^6$\r\n\r\n$1 \\le all_l \\le all_r \\le 10^{12}$"}]}