{"title":"ddd和骡马","time_limit":1000,"memory_limit":512,"tags":["2020校赛模拟赛"],"operation":{"submit":"https://oj.xjtuicpc.com/problem/1140#submit_code","submissions":"https://oj.xjtuicpc.com/submissions?problem_id=1140","statistics":"https://oj.xjtuicpc.com/problem/1140/statistics/fastest","testdata":"https://oj.xjtuicpc.com/problem/1140/testdata","discussion":"https://oj.xjtuicpc.com/discussion/problem/1140"},"statement":[{"title":"题目描述","type":"description","format":"markdown","require":["katex"],"content":"$\\text{ddd}$被一群骡子和马儿拦住了去路，动物们听说$\\text{ddd}$是世界上最聪明的人，于是请他解决一个问题。\r\n\r\n一共有$n$匹骡子和$n$匹马儿，他们分别从$1$-$n$编号，如果一匹骡子和一匹马的编号在十进制下各位上的数求和相同，就称他们是精神骡马，简称精骡。那么，一共有多少对组合是满足这样的条件的呢？\r\n\r\n如果$\\text{ddd}$能够解决这个问题，则骡子和马儿愿意尊$\\text{ddd}$为皇帝，国号为骡马$\\text{d}$国"},{"title":"输入格式","type":"input_format","format":"markdown","require":["katex"],"content":"输入仅一行，为一个整数$n$。"},{"title":"输出格式","type":"output_format","format":"markdown","require":["katex"],"content":"答案仅一行，为精骡组合的数量。"},{"title":"样例","type":"example","format":"markdown","require":["katex"],"content":"#### 样例输入\r\n```plain\r\n11\r\n```\r\n\r\n#### 样例输出\r\n```plain\r\n15\r\n```\r\n\r\n#### 样例解释\r\n```\r\n所有合法的组合：\r\n{1,1},{2,2},{3,3},{4,4},{5,5},{6,6},{7,7},{8,8},{9,9},{1,10},{10,1},{10,10},{2,11},{11,2},{11,11}\r\n```"},{"title":"数据范围与提示","type":"limit_and_hint","format":"markdown","require":["katex"],"content":"$1 \\leq n \\leq 10^5$"}]}