{"title":"「FJSC2018PJD10T4」最短路","time_limit":1000,"memory_limit":256,"tags":[],"operation":{"submit":"https://oj.iqzsy.xyz/problem/5102#submit_code","submissions":"https://oj.iqzsy.xyz/submissions?problem_id=5102","statistics":"https://oj.iqzsy.xyz/problem/5102/statistics/fastest","testdata":"https://oj.iqzsy.xyz/problem/5102/testdata","discussion":"https://oj.iqzsy.xyz/discussion/problem/5102"},"statement":[{"title":"题目描述","type":"description","format":"markdown","require":["katex"],"content":"众所周知，小y喜欢旅游。\r\n\n\r\n\n这次，他到了A星球。A星球上有 $n$ 个城市，城市之间存在有向边。经过每条边有一个时间 $t_i$。小y想从 $1$ 号城市走到 $n$ 号城市。他想知道从 $1$ 号城市到 $n$ 号城市的最少花费时间。\r\n\n\r\n\n小y又跟A球星的霸主py了一下。他现在有一种魔法，每次可以把一条边的时间取反（相当于时间穿梭）。但这种魔法最多只能使用 $K$ 次。并且小y经过使用魔法的边后魔法就会消失，但可以再次对这条边使用魔法。现在他又想知道从 $1$ 号城市到 $n$ 号城市的最少花费时间是多少(可以为负)。\r\n\n"},{"title":"输入格式","type":"input_format","format":"markdown","require":["katex"],"content":"输入的第一行为 $n, m, K$ ，分别表示城市个数、有向边条数还有使用魔法次数。\r\n\n\r\n\n接下来 $m$ 行，每行三个整数 $x, y, z$，分别表示有向边 $(x, y)$ ，经过时间 $z$。\r\n\n"},{"title":"输出格式","type":"output_format","format":"markdown","require":["katex"],"content":"一行整数表示最短路。"},{"title":"样例","type":"example","format":"markdown","require":["katex"],"content":"### 样例输入1\r\n``` plain\r\n4 3 2\r\n1 2 5\r\n2 3 4\r\n3 4 1\r\n```\r\n### 样例输出1\r\n``` plain\r\n-8\r\n```\r\n"},{"title":"数据范围与提示","type":"limit_and_hint","format":"markdown","require":["katex"],"content":"对于 30%的数据: $n \\le 5, m \\le 20, K \\le 3$\r\n\n\r\n\n对于 60%的数据: $n \\le 20, m \\le 200, K \\le 100$\r\n\n\r\n\n对于100%的数据: $n \\le 50, m \\le 2500, K \\le 10^9, z > 0$\r\n\n"}]}