{"title":"数塔","time_limit":1000,"memory_limit":128,"tags":["动态规划"],"operation":{"submit":"https://lyoi.cc/problem/13#submit_code","submissions":"https://lyoi.cc/submissions?problem_id=13","statistics":"https://lyoi.cc/problem/13/statistics/fastest","testdata":"https://lyoi.cc/problem/13/testdata","discussion":"https://lyoi.cc/discussion/problem/13"},"statement":[{"title":"题目描述","type":"description","format":"markdown","require":["katex"],"content":"从数塔顶部出发，在每一节点选择向下走或向右下走，停在最后一行。要求找到一个路径，使路径总和最大。"},{"title":"输入格式","type":"input_format","format":"markdown","require":["katex"],"content":"第一行输入一正整数 $ n $。\r\n\r\n接下来，对于第 $ i $ 行，输入 $ i - 1 $ 个整数。"},{"title":"输出格式","type":"output_format","format":"markdown","require":["katex"],"content":"一行一个字符串，`max=` 后跟最大总和。"},{"title":"样例","type":"example","format":"markdown","require":["katex"],"content":"#### 输入样例\r\n```plain\r\n5\r\n13\r\n11 8\r\n12 7 26\r\n6 14 1 8\r\n12 7 13 24 11\r\n```\r\n\r\n#### 输出样例\r\n```plain\r\nmax=79\r\n```"},{"title":"数据范围与提示","type":"limit_and_hint","format":"markdown","require":["katex"],"content":"对于 $ 40\\% $ 的数据，$ n < 20 $；  \r\n对于 $ 60\\% $ 的数据，$ n < 60 $。"}]}